libpybee/Library.py
libpybee/Playlist.py
libpybee/Track.py
libpybee/__init__.py
libpybee-0.2.1.dist-info/LICENSE
libpybee-0.2.1.dist-info/METADATA
libpybee-0.2.1.dist-info/WHEEL
libpybee-0.2.1.dist-info/entry_points.txt
libpybee-0.2.1.dist-info/top_level.txt
libpybee-0.2.1.dist-info/RECORD
