Metadata-Version: 2.1
Name: libpybee
Version: 0.2.1
Summary: MusicBee Library Parser in Python (based on Liam Kaufman's "libpytunes")
Home-page: https://github.com/Dyl-M/libpybee
Author: Dylan "dyl-m" Monfret
Author-email: dyl_m.dev@proton.me
Classifier: Programming Language :: Python :: 3
Classifier: License :: OSI Approved :: MIT License
Classifier: Operating System :: OS Independent
Requires-Python: >=3.8
License-File: LICENSE
Requires-Dist: unidecode>=1.4.0
Provides-Extra: dev
Requires-Dist: flakes; extra == "dev"
Requires-Dist: pytest; extra == "dev"
Requires-Dist: pytest-cov; extra == "dev"
